rtl/control_unit/control_unit.v


module control_unit(
    input  wire [6:0] OPCODE,
    input  wire [2:0] FUNC3,
    input  wire [6:0] FUNC7,
    output reg        WRITE_ENABLE,
    output reg        MEM_WRITE,
    output reg        MEM_READ,
    output reg        BRANCH,
    output reg        JUMP,
    output reg        MUX_2_PC_SELECT, // PC_SELECT, // MUX_2
    output reg        MUX_1_IMM_SELECT, // IMM_SELECT, // MUX_1
    output reg        MUX_3_JAL_SELECT, // JAL_SELECT, // MUX_3
    output reg        MUX_4_DATA_MEM_SELECT, // DATA_MEM_SELECT, // MUX_4
    output reg [2:0]  ALU_OP
);
    // always block * to run the block whenever any input changes
    always @(*)
    begin
        // Default values
        WRITE_ENABLE = 1'b0;
        MEM_WRITE = 1'b0;
        MEM_READ = 1'b0;
        BRANCH = 1'b0;
        JUMP = 1'b0;
        MUX_2_PC_SELECT = 1'b0;
        MUX_1_IMM_SELECT = 1'b1;
        MUX_3_JAL_SELECT = 1'b0;
        MUX_4_DATA_MEM_SELECT = 1'b0;
        ALU_OP = 3'b000;

        case (OPCODE)

        //////////////////////////////////////////////////// R-type //////////////////////////////////////////////////////////////////
        8'b0110011:
            begin
                WRITE_ENABLE = 1'b1;
            end

        //////////////////////////////////////////////////// I-type //////////////////////////////////////////////////////////////////
        8'b0000011:
            if (FUNC3 == 3'b000 || // LB
                FUNC3 == 3'b001 || // LH
                FUNC3 == 3'b010 || // LW
                FUNC3 == 3'b100 || // LBU
                FUNC3 == 3'b101)   // LHU
                begin
                    MUX_1_IMM_SELECT = 1'b1;
                    WRITE_ENABLE = 1'b1;
                    MEM_READ = 1'b1;
                    ALU_OP = 3'b001;
                    MUX_4_DATA_MEM_SELECT = 1'b1;
                end
        8'b1100111:
            case (FUNC3)
            3'b000: // JALR
            begin
                WRITE_ENABLE = 1'b1;
                MUX_3_JAL_SELECT = 1'b1;
                MUX_1_IMM_SELECT = 1'b1;
                JUMP = 1'b1;
                ALU_OP = 3'b010;
                // Set the LSB of the calculated address to 0 to ensure it is word-aligned.
            end
            endcase
        8'b0010011:
            if (FUNC3 == 3'b000 || // ADDI
                FUNC3 == 3'b010 || // SLTI
                FUNC3 == 3'b011 || // SLTIU
                FUNC3 == 3'b100 || // XORI
                FUNC3 == 3'b110 || // ORI
                FUNC3 == 3'b111)   // ANDI
            begin
                WRITE_ENABLE = 1'b1;
                MUX_1_IMM_SELECT = 1'b1;
                ALU_OP = 3'b011;
            end
            
            else if ((FUNC7 == 7'b0000000 && FUNC3 == 3'b001) || // SLLI
                (FUNC7 == 7'b0000000 && FUNC3 == 3'b101) || // SRLI
                (FUNC7 == 7'b0100000 && FUNC3 == 3'b101))   // SRAI
            begin
                WRITE_ENABLE = 1'b1;
                MUX_1_IMM_SELECT = 1'b1;
                ALU_OP = 3'b011;
            end

        //////////////////////////////////////////////////// S-type //////////////////////////////////////////////////////////////////
        8'b0100011:
            case (FUNC3)
            3'b000: // SB
            begin
                MEM_WRITE = 1'b1;
                MUX_1_IMM_SELECT = 1'b1;
                ALU_OP = 3'b100;
            end
            3'b001: // SH
            begin
                MEM_WRITE = 1'b1;
                MUX_1_IMM_SELECT = 1'b1;
                ALU_OP = 3'b100;
            end
            3'b010: // SW
            begin
                MEM_WRITE = 1'b1;
                MUX_1_IMM_SELECT = 1'b1;
                ALU_OP = 3'b100;
            end
            endcase

        //////////////////////////////////////////////////// U-type //////////////////////////////////////////////////////////////////
        8'b0110111: // LUI
            begin
            WRITE_ENABLE = 1'b1;
            MUX_1_IMM_SELECT = 1'b1;
            ALU_OP     = 3'b101;
            end
        8'b0010111: // AUIPC
            begin
            WRITE_ENABLE = 1'b1;
            MUX_1_IMM_SELECT = 1'b1;
            MUX_2_PC_SELECT = 1'b1;
            ALU_OP = 3'b100;
            end

        //////////////////////////////////////////////////// B-type //////////////////////////////////////////////////////////////////
        8'b1100011:
            if (FUNC3 == 3'b000 || // BEQ
                FUNC3 == 3'b001 || // BNE
                FUNC3 == 3'b100 || // BLT
                FUNC3 == 3'b101 || // BGE
                FUNC3 == 3'b110 || // BLTU
                FUNC3 == 3'b111)   // BGEU
            begin
                BRANCH = 1'b1;
                MUX_2_PC_SELECT = 1'b1;
                MUX_1_IMM_SELECT = 1'b1;
                ALU_OP = 3'b100;
            end


        //////////////////////////////////////////////////// J-type //////////////////////////////////////////////////////////////////
        8'b1101111: // JAL
            begin
            JUMP = 1'b1;
            MUX_3_JAL_SELECT = 1'b1;
            MUX_2_PC_SELECT = 1'b1;
            MUX_1_IMM_SELECT = 1'b1;
            WRITE_ENABLE = 1'b1;
            ALU_OP = 3'b100;
            end
        endcase

    end

endmodule

tb/control_unit_tb/control_unit_tb.v
`include "../../rtl/control_unit/control_unit.v"

`timescale 1ns / 1ps
module control_unit_tb;
    // Inputs
    reg [6:0] OPCODE;
    reg [2:0] FUNC3;
    reg [6:0] FUNC7;

    // Outputs
    wire WRITE_ENABLE;
    wire MEM_WRITE;
    wire MEM_READ;
    wire BRANCH;
    wire JUMP;
    wire MUX_2_PC_SELECT;
    wire MUX_1_IMM_SELECT;
    wire MUX_3_JAL_SELECT;
    wire MUX_4_DATA_MEM_SELECT;

    // Instantiate the Unit Under Test (UUT)
    control_unit uut (
        .OPCODE(OPCODE), 
        .FUNC3(FUNC3), 
        .FUNC7(FUNC7), 
        .WRITE_ENABLE(WRITE_ENABLE), 
        .MEM_WRITE(MEM_WRITE), 
        .MEM_READ(MEM_READ), 
        .BRANCH(BRANCH), 
        .JUMP(JUMP), 
        .MUX_2_PC_SELECT(MUX_2_PC_SELECT), 
        .MUX_1_IMM_SELECT(MUX_1_IMM_SELECT),
        .MUX_3_JAL_SELECT(MUX_3_JAL_SELECT), 
        .MUX_4_DATA_MEM_SELECT(MUX_4_DATA_MEM_SELECT)
    );

    initial begin
        // Initialize Inputs
        OPCODE = 0;
        FUNC3 = 0;
        FUNC7 = 0;

        // Open VCD file for GTKWave
        $dumpfile("control_unit_tb.vcd");
        $dumpvars(0, control_unit_tb);

        // Wait 100 ns for global reset to finish
        #10;
        
        // Test R-type instructions
        OPCODE = 8'b0110011;
        FUNC3 = 3'b000; FUNC7 = 7'b0000000; #10; // ADD
        FUNC3 = 3'b000; FUNC7 = 7'b0100000; #10; // SUB
        FUNC3 = 3'b001; FUNC7 = 7'b0000000; #10; // SLL
        FUNC3 = 3'b010; FUNC7 = 7'b0000000; #10; // SLT
        FUNC3 = 3'b011; FUNC7 = 7'b0000000; #10; // SLTU
        FUNC3 = 3'b100; FUNC7 = 7'b0000000; #10; // XOR
        FUNC3 = 3'b101; FUNC7 = 7'b0000000; #10; // SRL
        FUNC3 = 3'b101; FUNC7 = 7'b0100000; #10; // SRA
        FUNC3 = 3'b110; FUNC7 = 7'b0000000; #10; // OR
        FUNC3 = 3'b111; FUNC7 = 7'b0000000; #10; // AND

        // Test I-type instructions
        OPCODE = 8'b0000011;
        FUNC3 = 3'b000; #10; // LB
        FUNC3 = 3'b001; #10; // LH
        FUNC3 = 3'b010; #10; // LW
        FUNC3 = 3'b100; #10; // LBU
        FUNC3 = 3'b101; #10; // LHU

        OPCODE = 8'b1100111;
        FUNC3 = 3'b000; #10; // JALR

        OPCODE = 8'b0010011;
        FUNC3 = 3'b000; #10; // ADDI
        FUNC3 = 3'b010; #10; // SLTI
        FUNC3 = 3'b011; #10; // SLTIU
        FUNC3 = 3'b100; #10; // XORI
        FUNC3 = 3'b110; #10; // ORI
        FUNC3 = 3'b111; #10; // ANDI
        FUNC3 = 3'b001; FUNC7 = 7'b0000000; #10; // SLLI
        FUNC3 = 3'b101; FUNC7 = 7'b0000000; #10; // SRLI
        FUNC3 = 3'b101; FUNC7 = 7'b0100000; #10; // SRAI

        // Test S-type instructions
        OPCODE = 8'b0100011;
        FUNC3 = 3'b000; #10; // SB
        FUNC3 = 3'b001; #10; // SH
        FUNC3 = 3'b010; #10; // SW

        // Test U-type instructions
        OPCODE = 8'b0110111; #10; // LUI
        OPCODE = 8'b0010111; #10; // AUIPC

        // Test B-type instructions
        OPCODE = 8'b1100011;
        FUNC3 = 3'b000; #10; // BEQ
        FUNC3 = 3'b001; #10; // BNE
        FUNC3 = 3'b100; #10; // BLT
        FUNC3 = 3'b101; #10; // BGE
        FUNC3 = 3'b110; #10; // BLTU
        FUNC3 = 3'b111; #10; // BGEU

        // Test J-type instruction
        OPCODE = 8'b1101111; #10; // JAL


        OPCODE = 8'b0010011;
        FUNC3 = 3'b000; #10; // NOP when rd -> x0 ; rs1 -> x0 ; imm -> 0
        $finish; // $stop; only pauses the simulation
    end
      
endmodule

tb/control_unit_tb/control_unit_tb.vcd
$date
	Wed Jun 25 23:13:44 2025
$end
$version
	Icarus Verilog
$end
$timescale
	1ps
$end
$scope module control_unit_tb $end
$var wire 1 ! WRITE_ENABLE $end
$var wire 1 " MUX_4_DATA_MEM_SELECT $end
$var wire 1 # MUX_3_JAL_SELECT $end
$var wire 1 $ MUX_2_PC_SELECT $end
$var wire 1 % MUX_1_IMM_SELECT $end
$var wire 1 & MEM_WRITE $end
$var wire 1 ' MEM_READ $end
$var wire 1 ( JUMP $end
$var wire 1 ) BRANCH $end
$var reg 3 * FUNC3 [2:0] $end
$var reg 7 + FUNC7 [6:0] $end
$var reg 7 , OPCODE [6:0] $end
$scope module uut $end
$var wire 3 - FUNC3 [2:0] $end
$var wire 7 . FUNC7 [6:0] $end
$var wire 7 / OPCODE [6:0] $end
$var reg 3 0 ALU_OP [2:0] $end
$var reg 1 ) BRANCH $end
$var reg 1 ( JUMP $end
$var reg 1 ' MEM_READ $end
$var reg 1 & MEM_WRITE $end
$var reg 1 % MUX_1_IMM_SELECT $end
$var reg 1 $ MUX_2_PC_SELECT $end
$var reg 1 # MUX_3_JAL_SELECT $end
$var reg 1 " MUX_4_DATA_MEM_SELECT $end
$var reg 1 ! WRITE_ENABLE $end
$upscope $end
$upscope $end
$enddefinitions $end
$comment Show the parameter values. $end
$dumpall
$end
#0
$dumpvars
b0 0
b0 /
b0 .
b0 -
b0 ,
b0 +
b0 *
0)
0(
0'
0&
1%
0$
0#
0"
0!
$end
#10000
1!
b110011 ,
b110011 /
#20000
1!
b100000 +
b100000 .
#30000
1!
b0 +
b0 .
b1 *
b1 -
#40000
1!
b10 *
b10 -
#50000
1!
b11 *
b11 -
#60000
1!
b100 *
b100 -
#70000
1!
b101 *
b101 -
#80000
1!
b100000 +
b100000 .
#90000
1!
b0 +
b0 .
b110 *
b110 -
#100000
1!
b111 *
b111 -
#110000
1"
b1 0
1'
1!
b0 *
b0 -
b11 ,
b11 /
#120000
b1 0
1"
1'
1!
b1 *
b1 -
#130000
b1 0
1"
1'
1!
b10 *
b10 -
#140000
b1 0
1"
1'
1!
b100 *
b100 -
#150000
b1 0
1"
1'
1!
b101 *
b101 -
#160000
1(
1#
b10 0
0"
0'
1!
b0 *
b0 -
b1100111 ,
b1100111 /
#170000
b11 0
0#
0(
1!
b10011 ,
b10011 /
#180000
b11 0
1!
b10 *
b10 -
#190000
b11 0
1!
b11 *
b11 -
#200000
b11 0
1!
b100 *
b100 -
#210000
b11 0
1!
b110 *
b110 -
#220000
b11 0
1!
b111 *
b111 -
#230000
b11 0
1!
b1 *
b1 -
#240000
b11 0
1!
b101 *
b101 -
#250000
b11 0
1!
b100000 +
b100000 .
#260000
1&
b100 0
0!
b0 *
b0 -
b100011 ,
b100011 /
#270000
b100 0
1&
b1 *
b1 -
#280000
b100 0
1&
b10 *
b10 -
#290000
1!
b101 0
0&
b110111 ,
b110111 /
#300000
1$
b100 0
1!
b10111 ,
b10111 /
#310000
1)
b100 0
1$
0!
b0 *
b0 -
b1100011 ,
b1100011 /
#320000
b100 0
1$
1)
b1 *
b1 -
#330000
b100 0
1$
1)
b100 *
b100 -
#340000
b100 0
1$
1)
b101 *
b101 -
#350000
b100 0
1$
1)
b110 *
b110 -
#360000
b100 0
1$
1)
b111 *
b111 -
#370000
1!
1#
1(
b100 0
1$
0)
b1101111 ,
b1101111 /
#380000
b11 0
0#
0$
0(
1!
b0 *
b0 -
b10011 ,
b10011 /
