rtl/register_file/register_file.v
module register_file (
    input wire CLK,                    // Clock signal
    input wire RST,                    // Reset signal
    input wire WRITE_ENABLE,           // Write enable signal
    input wire [4:0] READ_REG_1,        // Read register 1 address
    input wire [4:0] READ_REG_2,        // Read register 2 address
    input wire [4:0] WRITE_REG,        // Write register address
    input wire [31:0] WRITE_DATA,      // Data to write
    output wire [31:0] READ_DATA_1,     // Data from read register 1
    output wire [31:0] READ_DATA_2      // Data from read register 2
);

    // Register array with initialization
    reg [31:0] REGISTERS [31:0];
    integer i;     // Declare loop variable outside the procedural block for Verilog compatibility

    initial begin
        for (i = 0; i < 32; i = i + 1)
            REGISTERS[i] = 32'b0;
    end

    // Read logic
    assign READ_DATA_1 = (READ_REG_1 != 0) ? REGISTERS[READ_REG_1] : 32'b0; // R0 is always 0
    assign READ_DATA_2 = (READ_REG_2 != 0) ? REGISTERS[READ_REG_2] : 32'b0;

    // Synchronous reset and write logic
    always @(posedge CLK) begin
        if (RST) begin
            for (i = 0; i < 32; i = i + 1)
                REGISTERS[i] <= 32'b0;
        end
        else if (WRITE_ENABLE && WRITE_REG != 32'b00000000_00000000_00000000_00000000)
            REGISTERS[WRITE_REG] <= WRITE_DATA;
    end

endmodule

rtl/register_file/register_file_tb.v
`include "register_file.v"
// Testbench for the register file module
module register_file_tb();

    // Testbench signals
    reg CLK, RST, WRITE_ENABLE;
    reg [4:0] READ_REG_1, READ_REG_2, WRITE_REG;
    reg [31:0] WRITE_DATA;
    wire [31:0] READ_DATA_1, READ_DATA_2;
    
    // Instantiate register file
    register_file dut (
        .CLK(CLK),
        .RST(RST),
        .WRITE_ENABLE(WRITE_ENABLE),
        .READ_REG_1(READ_REG_1),
        .READ_REG_2(READ_REG_2),
        .WRITE_REG(WRITE_REG),
        .WRITE_DATA(WRITE_DATA),
        .READ_DATA_1(READ_DATA_1),
        .READ_DATA_2(READ_DATA_2)
    );

    // Clock generation
    initial begin
        CLK = 0;
        forever #5 CLK = ~CLK;
    end

    // Test stimulus
    initial begin
        // Initialize waveform dump
        $dumpfile("register_file_tb.vcd");
        $dumpvars(0, register_file_tb);
        
        // Initialize signals
        RST = 0;
        WRITE_ENABLE = 0;
        READ_REG_1 = 0;
        READ_REG_2 = 0;
        WRITE_REG = 0;
        WRITE_DATA = 0;

        // Test 1: Reset
        RST = 1;
        @(posedge CLK);
        RST = 0;
        
        // Test 2: Write to register 1 and read back
        @(posedge CLK);
        WRITE_ENABLE = 1;
        WRITE_REG = 5'd1;
        WRITE_DATA = 32'hAAAA_AAAA;
        @(posedge CLK);
        WRITE_ENABLE = 0;
        READ_REG_1 = 5'd1;
        @(posedge CLK);
        if (READ_DATA_1 !== 32'hAAAA_AAAA)
            $display("Test 2 Failed: Expected 0xAAAAAAAA, Got %h", READ_DATA_1);

        // Test 3: Write to register 0 (should be ignored)
        @(posedge CLK);
        WRITE_ENABLE = 1;
        WRITE_REG = 5'd0;
        WRITE_DATA = 32'hFFFF_FFFF;
        @(posedge CLK);
        WRITE_ENABLE = 0;
        READ_REG_1 = 5'd0;
        @(posedge CLK);
        if (READ_DATA_1 !== 32'h0)
            $display("Test 3 Failed: Register 0 should always be 0");

        // Test 4: Simultaneous read and write to same register
        @(posedge CLK);
        WRITE_ENABLE = 1;
        WRITE_REG = 5'd2;
        WRITE_DATA = 32'h5555_5555;
        READ_REG_1 = 5'd2;
        READ_REG_2 = 5'd1;
        @(posedge CLK);
        if (READ_DATA_2 !== 32'hAAAA_AAAA)
            $display("Test 4 Failed: Incorrect value read from register 1");

        // End simulation
        #20 $finish;
    end

endmodule

tb/register_file_tb/register_file_tb.vcd
$date
	Sat Jun 07 00:50:31 2025
$end
$version
	Icarus Verilog
$end
$timescale
	1s
$end
$scope module register_file_tb $end
$var wire 32 ! READ_DATA_2 [31:0] $end
$var wire 32 " READ_DATA_1 [31:0] $end
$var reg 1 # CLK $end
$var reg 5 $ READ_REG_1 [4:0] $end
$var reg 5 % READ_REG_2 [4:0] $end
$var reg 1 & RST $end
$var reg 32 ' WRITE_DATA [31:0] $end
$var reg 1 ( WRITE_ENABLE $end
$var reg 5 ) WRITE_REG [4:0] $end
$scope module dut $end
$var wire 1 # CLK $end
$var wire 5 * READ_REG_1 [4:0] $end
$var wire 5 + READ_REG_2 [4:0] $end
$var wire 1 & RST $end
$var wire 32 , WRITE_DATA [31:0] $end
$var wire 1 ( WRITE_ENABLE $end
$var wire 5 - WRITE_REG [4:0] $end
$var wire 32 . READ_DATA_2 [31:0] $end
$var wire 32 / READ_DATA_1 [31:0] $end
$var integer 32 0 i [31:0] $end
$upscope $end
$upscope $end
$enddefinitions $end
$comment Show the parameter values. $end
$dumpall
$end
#0
$dumpvars
b100000 0
b0 /
b0 .
b0 -
b0 ,
b0 +
b0 *
b0 )
0(
b0 '
1&
b0 %
b0 $
0#
b0 "
b0 !
$end
#5
0&
1#
#10
0#
#15
b10101010101010101010101010101010 '
b10101010101010101010101010101010 ,
b1 )
b1 -
1(
1#
#20
0#
#25
b1 $
b1 *
0(
1#
#30
0#
#35
1#
#40
0#
#45
b11111111111111111111111111111111 '
b11111111111111111111111111111111 ,
b0 )
b0 -
1(
1#
#50
0#
#55
b0 $
b0 *
0(
1#
#60
0#
#65
1#
#70
0#
#75
b1 %
b1 +
b10 $
b10 *
b1010101010101010101010101010101 '
b1010101010101010101010101010101 ,
b10 )
b10 -
1(
1#
#80
0#
#85
b1010101010101010101010101010101 "
b1010101010101010101010101010101 /
1#
